scaffold/__init__.py
scaffold/bus.py
scaffold/cli.py
scaffold/iso7816.py
scaffold/stm32.py
donjon_scaffold-0.9.5.dist-info/COPYING
donjon_scaffold-0.9.5.dist-info/COPYING.LESSER
donjon_scaffold-0.9.5.dist-info/METADATA
donjon_scaffold-0.9.5.dist-info/WHEEL
donjon_scaffold-0.9.5.dist-info/entry_points.txt
donjon_scaffold-0.9.5.dist-info/RECORD
