Metadata-Version: 2.3
Name: donjon-scaffold
Version: 0.9.5
Summary: Python3 API for the Scaffold board
License: LGPL-3.0-or-later
Keywords: scaffold,donjon,ledger
Author: Olivier Hériveaux
Author-email: olivier.heriveaux@ledger.fr
Requires-Python: >=3.9,<4.0
Classifier: Development Status :: 5 - Production/Stable
Classifier: Intended Audience :: Science/Research
Classifier: License :: OSI Approved :: GNU Lesser General Public License v3 or later (LGPLv3+)
Classifier: Programming Language :: Python :: 3
Classifier: Programming Language :: Python :: 3.9
Classifier: Programming Language :: Python :: 3.10
Classifier: Programming Language :: Python :: 3.11
Classifier: Programming Language :: Python :: 3.12
Classifier: Programming Language :: Python :: 3.13
Classifier: Topic :: Scientific/Engineering
Classifier: Topic :: Security
Classifier: Topic :: System :: Hardware
Requires-Dist: crcmod
Requires-Dist: packaging
Requires-Dist: pyserial
Requires-Dist: requests
Requires-Dist: rich
Requires-Dist: rich-argparse
Project-URL: Documentation, https://donjonscaffold.readthedocs.io
Project-URL: Repository, https://github.com/Ledger-Donjon/scaffold/
